{"id":1440,"disenchantingSkillRank":1,"description":"","name":"Gnoll Skull Basher","icon":"inv_hammer_11","stackable":1,"itemBind":2,"bonusStats":[{"stat":4,"amount":3},{"stat":7,"amount":3}],"itemSpells":[],"buyPrice":6152,"itemClass":2,"itemSubClass":4,"containerSlots":0,"weaponInfo":{"damage":{"min":9,"max":18,"exactMin":9.0,"exactMax":18.0},"weaponSpeed":2.7,"dps":5.0},"inventoryType":13,"equippable":true,"itemLevel":19,"maxCount":0,"maxDurability":55,"minFactionId":0,"minReputation":0,"quality":2,"sellPrice":1230,"requiredSkill":0,"requiredLevel":14,"requiredSkillRank":0,"itemSource":{"sourceId":0,"sourceType":"NONE"},"baseArmor":0,"hasSockets":false,"isAuctionable":true,"armor":0,"displayInfoId":8570,"nameDescription":"","nameDescriptionColor":"000000","upgradable":true,"heroicTooltip":false,"context":"","bonusLists":[],"availableContexts":[""],"bonusSummary":{"defaultBonusLists":[],"chanceBonusLists":[],"bonusChances":[]}}