{"id":1503,"description":"","name":"Warped Leather Boots","icon":"inv_boots_05","stackable":1,"itemBind":0,"bonusStats":[],"itemSpells":[],"buyPrice":764,"itemClass":4,"itemSubClass":2,"containerSlots":0,"inventoryType":8,"equippable":true,"itemLevel":15,"maxCount":0,"maxDurability":40,"minFactionId":0,"minReputation":0,"quality":0,"sellPrice":152,"requiredSkill":0,"requiredLevel":10,"requiredSkillRank":0,"itemSource":{"sourceId":0,"sourceType":"NONE"},"baseArmor":6,"hasSockets":false,"isAuctionable":true,"armor":6,"displayInfoId":14846,"nameDescription":"","nameDescriptionColor":"000000","upgradable":true,"heroicTooltip":false,"context":"","bonusLists":[],"availableContexts":[""],"bonusSummary":{"defaultBonusLists":[],"chanceBonusLists":[],"bonusChances":[]}}