{"id":1743,"description":"","name":"Laced Mail Pants","icon":"inv_pants_03","stackable":1,"itemBind":0,"bonusStats":[],"itemSpells":[],"buyPrice":1748,"itemClass":4,"itemSubClass":3,"containerSlots":0,"inventoryType":7,"equippable":true,"itemLevel":19,"maxCount":0,"maxDurability":70,"minFactionId":0,"minReputation":0,"quality":0,"sellPrice":349,"requiredSkill":0,"requiredLevel":14,"requiredSkillRank":0,"itemSource":{"sourceId":0,"sourceType":"NONE"},"baseArmor":12,"hasSockets":false,"isAuctionable":true,"armor":12,"displayInfoId":687,"nameDescription":"","nameDescriptionColor":"000000","upgradable":true,"heroicTooltip":false,"context":"","bonusLists":[],"availableContexts":[""],"bonusSummary":{"defaultBonusLists":[],"chanceBonusLists":[],"bonusChances":[]}}