{"id":2132,"description":"","name":"Short Staff","icon":"inv_staff_02","stackable":1,"itemBind":0,"bonusStats":[],"itemSpells":[],"buyPrice":103,"itemClass":2,"itemSubClass":10,"containerSlots":0,"weaponInfo":{"damage":{"min":4,"max":6,"exactMin":4.0,"exactMax":6.0},"weaponSpeed":3.2,"dps":1.5625},"inventoryType":17,"equippable":true,"itemLevel":4,"maxCount":0,"maxDurability":30,"minFactionId":0,"minReputation":0,"quality":1,"sellPrice":20,"requiredSkill":0,"requiredLevel":1,"requiredSkillRank":0,"itemSource":{"sourceId":78,"sourceType":"VENDOR"},"baseArmor":0,"hasSockets":false,"isAuctionable":true,"armor":0,"displayInfoId":20438,"nameDescription":"","nameDescriptionColor":"000000","upgradable":true,"heroicTooltip":false,"context":"","bonusLists":[],"availableContexts":[""],"bonusSummary":{"defaultBonusLists":[],"chanceBonusLists":[],"bonusChances":[]}}