{"id":2220,"description":"","name":"Box Shield","icon":"inv_shield_03","stackable":1,"itemBind":0,"bonusStats":[],"itemSpells":[],"buyPrice":2596,"itemClass":4,"itemSubClass":6,"containerSlots":0,"inventoryType":14,"equippable":true,"itemLevel":23,"maxCount":0,"maxDurability":70,"minFactionId":0,"minReputation":0,"quality":0,"sellPrice":519,"requiredSkill":0,"requiredLevel":18,"requiredSkillRank":0,"itemSource":{"sourceId":0,"sourceType":"NONE"},"baseArmor":54,"hasSockets":false,"isAuctionable":true,"armor":54,"displayInfoId":18729,"nameDescription":"","nameDescriptionColor":"000000","upgradable":true,"heroicTooltip":false,"context":"","bonusLists":[],"availableContexts":[""],"bonusSummary":{"defaultBonusLists":[],"chanceBonusLists":[],"bonusChances":[]}}